LICENSE
README.md
pyproject.toml
setup.py
src/cocotb_bus/__init__.py
src/cocotb_bus/_version.py
src/cocotb_bus/bus.py
src/cocotb_bus/scoreboard.py
src/cocotb_bus/drivers/__init__.py
src/cocotb_bus/drivers/amba.py
src/cocotb_bus/drivers/avalon.py
src/cocotb_bus/drivers/opb.py
src/cocotb_bus/drivers/xgmii.py
src/cocotb_bus/monitors/__init__.py
src/cocotb_bus/monitors/avalon.py
src/cocotb_bus/monitors/xgmii.py
src/rapidstream_cocotb_bus.egg-info/PKG-INFO
src/rapidstream_cocotb_bus.egg-info/SOURCES.txt
src/rapidstream_cocotb_bus.egg-info/dependency_links.txt
src/rapidstream_cocotb_bus.egg-info/requires.txt
src/rapidstream_cocotb_bus.egg-info/top_level.txt