Metadata-Version: 2.1
Name: rapidstream-cocotb-bus
Version: 0.2.1
Home-page: https://github.com/rapidstream-da/cocotb-bus
Author: cocotb maintainers
Author-email: cocotb@lists.librecores.org
Requires-Python: >=3.5
License-File: LICENSE
Requires-Dist: rapidstream-cocotb<2.0,>=1.5.0.dev
